sumologic_opentelemetry/__init__.py
sumologic_opentelemetry/env.py
sumologic_opentelemetry-1.9.1.data/scripts/sumologic-opentelemetry-instrument
sumologic_opentelemetry-1.9.1.dist-info/LICENSE
sumologic_opentelemetry-1.9.1.dist-info/METADATA
sumologic_opentelemetry-1.9.1.dist-info/WHEEL
sumologic_opentelemetry-1.9.1.dist-info/top_level.txt
sumologic_opentelemetry-1.9.1.dist-info/zip-safe
sumologic_opentelemetry-1.9.1.dist-info/RECORD
