Metadata-Version: 2.1
Name: sumologic-opentelemetry
Version: 1.9.1
Summary: An all-in-one package for python projects used to enable OpenTelemetry auto-instrumentation
Home-page: https://github.com/SumoLogic/sumologic-opentelemetry-python
Author: Sumo Logic, Inc. Authors
Author-email: support@sumologic.com
License: Apache-2.0
Platform: UNKNOWN
Classifier: Development Status :: 4 - Beta
Classifier: License :: OSI Approved :: Apache Software License
Classifier: Programming Language :: Python
Classifier: Programming Language :: Python :: 3
Classifier: Programming Language :: Python :: 3.6
Classifier: Programming Language :: Python :: 3.7
Classifier: Programming Language :: Python :: 3.8
Classifier: Programming Language :: Python :: 3.9
Classifier: Programming Language :: Python :: 3.10
Requires-Python: >=3.6
Provides-Extra: all
License-File: LICENSE
